Metadata-Version: 1.1
Name: oim
Version: 0.1.4
Summary: A library for working with the Open Information Model
Home-page: UNKNOWN
Author: Mark Goodhand
Author-email: mrg-oim@corefiling.com
License: MIT
Keywords: oim xbrl
Platform: UNKNOWN
Classifier: Development Status :: 3 - Alpha
Classifier: Intended Audience :: Developers
Classifier: License :: OSI Approved :: MIT License
Classifier: Programming Language :: Python :: 2
Classifier: Programming Language :: Python :: 2.7
